<?xml version="1.0" encoding="UTF-8"?>
<!DOCTYPE databases PUBLIC 
  "-//EXOLAB/Castor Mapping DTD Version 1.0//EN"
  "http://castor.exolab.org/mapping.dtd">
<mapping>
	<description>Basic mapping example</description>
	<class name="com.cnaps.coreservices.CommonXMLEntity">
		<!-- the name of the xml file's root element  -->
		<map-to xml="Document" />

		<!-- 原发起服务名 -->
		<field name="source">
			<bind-xml name="Source" node="element"
				location="ResponseHead" />
		</field>
		<!--原接收服务名-->
		<field name="destination">
			<bind-xml name="Destination" node="element"
				location="ResponseHead" />
		</field>
		<!--原渠道报文标识号-->
		<field name="messageId">
			<bind-xml name="MessageId" node="element"
				location="ResponseHead" />
		</field>
		<!--原报文发送时间-->
		<field name="sendDateTime">
			<bind-xml name="SendDateTime" node="element"
				location="ResponseHead" />
		</field>
		<!--处理码-->
		<field name="processCode">
			<bind-xml name="ProcessCode" node="element"
				location="ResponseHead" />
		</field>
		<!--处理信息-->
		<field name="processDes">
			<bind-xml name="ProcessDes" node="element"
				location="ResponseHead" />
		</field>


		<!--查询代码-->
		<field name="queryCd">
			<bind-xml name="QueryCd" node="element"
				location="ResponseFields" />
		</field>
		<field name="turnPageBeginPos">
			<bind-xml name="TurnPageBeginPos" node="element"
				location="ResponseFields" />
		</field>
		<field name="turnPageShowNum">
			<bind-xml name="TurnPageShowNum" node="element"
				location="ResponseFields" />
		</field>
		<field name="results"
			type="com.cnaps.hvps.persistence.messages.Hvpsservicekindtypemanage"
			collection="arraylist">
			<bind-xml name="QryResult" node="element"
				location="ResponseFields/QryResults" />
		</field>
	</class>

	<class
		name="com.cnaps.hvps.persistence.messages.Hvpsservicekindtypemanage">
		<field name="id" type="java.lang.Long">
			<bind-xml name="Id" node="element" />
		</field>
		<field name="msgid" type="java.lang.String">
			<bind-xml name="MsgId" node="element" />
		</field>	
		<field name="credttm" type="java.lang.String">
			<bind-xml name="CreDtTm" node="element" />
		</field>
		<field name="instgdrctpty" type="java.lang.String">
			<bind-xml name="InstgDrctPty" node="element" />
		</field>
		<field name="instgindrctpty" type="java.lang.String">
			<bind-xml name="InstgIndrctPty" node="element" />
		</field>
		<field name="instddrctpty" type="java.lang.String">
			<bind-xml name="InstdDrctPty" node="element" />
		</field>
		<field name="instdindrctpty" type="java.lang.String">
			<bind-xml name="InstdIndrctPty" node="element" />
		</field>
		<field name="syscd" type="java.lang.String">
			<bind-xml name="SysCd" node="element" />
		</field>
		<field name="rmk" type="java.lang.String">
			<bind-xml name="Rmk" node="element" />
		</field>
						
		<field name="chngtp" type="java.lang.String">
			<bind-xml name="ChngTp" node="element" />
		</field>
		<field name="fctvtp" type="java.lang.String">
			<bind-xml name="FctvTp" node="element" />
		</field>
		<field name="fctvdt" type="java.lang.String">
			<bind-xml name="FctvDt" node="element" />
		</field>
		<field name="ifctvdt" type="java.lang.String">
			<bind-xml name="IfctvDt" node="element" />
		</field>
		
		<field name="msgtp" type="java.lang.String">
			<bind-xml name="MsgTp" node="element" />
		</field>
		<field name="msgnm" type="java.lang.String">
			<bind-xml name="MsgNm" node="element" />
		</field>
		<field name="txtpcd" type="java.lang.String">
			<bind-xml name="TxTpCd" node="element" />
		</field>
		<field name="txtpnm" type="java.lang.String">
			<bind-xml name="TxTpNm" node="element" />
		</field>
		<field name="ctgypurpcd" type="java.lang.String">
			<bind-xml name="CtgyPurpCd" node="element" />
		</field>
		<field name="ctgypurpnm" type="java.lang.String">
			<bind-xml name="CtgyPurpNm" node="element" />
		</field>
	</class>

</mapping>

