<?xml version="1.0" encoding="UTF-8"?>
<persistence version="2.1" xmlns="http://xmlns.jcp.org/xml/ns/persistence" xmlns:xsi="http://www.w3.org/2001/XMLSchema-instance" xsi:schemaLocation="http://xmlns.jcp.org/xml/ns/persistence http://xmlns.jcp.org/xml/ns/persistence/persistence_2_1.xsd">
	<persistence-unit name="hio-coffee">
		<class>model.OaSysApp</class>
		<class>model.OaSysButton</class>
		<class>model.OaSysDataPermission</class>
		<class>model.OaSysExternalcontact</class>
		<class>model.OaSysFuncPermission</class>
		<class>model.OaSysMenu</class>
		<class>model.OaSysOrganization</class>
		<class>model.OaSysRole</class>
		<class>model.OaSysUser</class>
		<class>model.OaSysUserPosition</class>
		<class>model.OaSysUserRole</class>
	</persistence-unit>
</persistence>
