<mxEditor>
	<Array as="templates">
		<add as="task">
			<Task label="新环节" description="" href=""  isAuto="0" acType="1" assignType="0">
				<mxCell vertex="1">
					<mxGeometry as="geometry" width="150" height="30"/>
				</mxCell>
			</Task>
		</add>

		<add as="shape">
			<Shape label="新环节" description="" href=""  isAuto="0" acType="1" assignType="0">
				<mxCell vertex="1">
					<mxGeometry as="geometry" width="150" height="30" />
				</mxCell>
			</Shape>
		</add>
		<add as="round">
			<Shape label="新环节" description="" href="" isAuto="0" acType="1" assignType="0">
				<mxCell vertex="1">
					<mxGeometry as="geometry" width="50" height="50" />
				</mxCell>
			</Shape>
		</add>
		<add as="condt">
			<Shape label="条件判断" description="" href="" isAuto="1" acType="9" assignType="">
				<mxCell vertex="1" style="ellipse">		
					<mxGeometry as="geometry" width="140" height="30"/>
				</mxCell>
			</Shape>
		</add>
	</Array>
</mxEditor>