<?xml version="1.0" encoding="UTF-8"?>
<!DOCTYPE databases PUBLIC 
  "-//EXOLAB/Castor Mapping DTD Version 1.0//EN"
  "http://castor.exolab.org/mapping.dtd">
<mapping>
	<description>银行本票挂失维护</description>


	<class name="com.cnaps.hvps.form.transfer.PersonCrashSpanBankExchangeForm">
		<map-to xml="Document" />
		<!-- 机构号 --><field name="orgCode"><bind-xml name="OrgCode" node="element" location="RequestHead"/></field>
		<!-- 原发起服务名 -->
		<field name="source">
			<bind-xml name="Source" node="element"
				location="RequestHead" />
		</field>
		<!--原接收服务名-->
		<field name="destination">
			<bind-xml name="Destination" node="element"
				location="RequestHead" />
		</field>
		<!--功能代码-->
		<field name="transactionId">
			<bind-xml name="TransactionId" node="element"
				location="RequestHead" />
		</field>

		<!--原报文发送时间-->
		<field name="sendDateTime">
			<bind-xml name="SendDateTime" node="element"
				location="RequestHead" />
		</field>
		<!--网点号-->
		<field name="brnchCd">
			<bind-xml name="BrnchCd" node="element"
				location="RequestHead" />
		</field>
		<!--终端号-->
		<field name="termId">
			<bind-xml name="TermId" node="element"
				location="RequestHead" />
		</field>
		<!--操作柜员-->
		<field name="operTeller">
			<bind-xml name="OperTeller" node="element"
				location="RequestHead" />
		</field>
		<!--提交代码-->
		<field name="po"
			type="com.cnaps.hvps.persistence.transfer.PersonCrashSpanBankExchange">
			<bind-xml name="RequestFields" node="element" />
		</field>
	</class>
		<class name="com.cnaps.hvps.persistence.transfer.PersonCrashSpanBankExchange">
		<!-- 本票流水号 -->
		<field name="paymentGrouppo">
			<bind-xml name="PaymentGrouppo" node="element"/>
		</field>
</class>
</mapping>

